yta_youtube_api/__init__.py
yta_youtube_api-0.0.1.dist-info/licenses/LICENSE
yta_youtube_api-0.0.1.dist-info/METADATA
yta_youtube_api-0.0.1.dist-info/WHEEL
yta_youtube_api-0.0.1.dist-info/RECORD
